{
  "os": {
    "apple": "macOS Catalina",
    "microsoft": "Windows 10",
    "linux": "Manjaro"
  },
  "tools": {
    "node-manager": "nvm",
    "package-manager": "Homebrew",
    "compression": "The Unarchiver",
    "wifi-password": "WiFi Password"
  },
  "primary": {
    "browser-1": "Firefox",
    "browser-2": "Chrome",
    "code-editor": "VS Code",
    "terminal": "iTerm2 + Spaceship + Navi"
  },
  "secondary": {
    "design-tool": "Figma",
    "todo-list": "Todoist",
    "rest-client": "Insomnia",
    "social": "Station"
  },
  "others": {
    "mind-maps": "MindNode",
    "video-player": "IINA",
    "music-player": "Spotify",
    "torrents": "WebTorrent",
    "cleaner": "Ccleaner",
    "usb-tools": "DiskMakerX",
    "ntfs": "Mounty",
    "gif-recorder": "Kap",
    "emoji-finder": "Rocket",
    "monitor-tool": "Spectacle",
    "screen-sharing": "Muzzle"
  }
}
